PyMVVM/__init__.py
PyMVVM/core.py
PyMVVM/decorators.py
PyMVVM/factory.py
pymvvm_design-0.6.0.dist-info/METADATA
pymvvm_design-0.6.0.dist-info/WHEEL
pymvvm_design-0.6.0.dist-info/top_level.txt
pymvvm_design-0.6.0.dist-info/RECORD
