Metadata-Version: 2.1
Name: pymvvm_design
Version: 0.6.0
Summary: A simplified MVVM framework for Python
Home-page: https://github.com/fridayowl/PyMVVM
Author: shinoj cm
Author-email: shinojcm01@gmail.com
Classifier: Development Status :: 3 - Alpha
Classifier: Intended Audience :: Developers
Classifier: License :: OSI Approved :: MIT License
Classifier: Operating System :: OS Independent
Classifier: Programming Language :: Python :: 3
Classifier: Programming Language :: Python :: 3.7
Classifier: Programming Language :: Python :: 3.8
Classifier: Programming Language :: Python :: 3.9
Requires-Python: >=3.7
